<?xml version="1.0" encoding="UTF-8"?>
<description xmlns="http://openoffice.org/extensions/description/2006" xmlns:d="http://openoffice.org/extensions/description/2006" xmlns:xlink="http://www.w3.org/1999/xlink">
	<version value="0.92"/>
	<identifier value="de.petanqueturniermanager"/>
	<update-information>
		<src xlink:href="https://github.com/michaelmassee/Petanque-Turnier-Manager/releases"/>
	</update-information>
	<publisher>
		<name lang="en" xlink:href="https://github.com/michaelmassee/Petanque-Turnier-Manager">Michael Massee</name>
		<name lang="de" xlink:href="https://github.com/michaelmassee/Petanque-Turnier-Manager">Michael Massee</name>
	</publisher>
	<display-name>
		<name lang="en">PetanqueTurnierManager</name>
		<name lang="de">PetanqueTurnierManager</name>
	</display-name>
	<extension-description>
		<src lang="en" xlink:href="description/desc_de.txt"/>
		<src lang="de" xlink:href="description/desc_de.txt"/>
	</extension-description>
</description>
